uk_modulus_check/__init__.py
uk_modulus_check/py.typed
uk_modulus_check/sort_code_substitution_table.py
uk_modulus_check/uk_modulus_checker.py
uk_modulus_check/weight_table.py
uk_modulus_check-0.0.1.dist-info/LICENSE
uk_modulus_check-0.0.1.dist-info/METADATA
uk_modulus_check-0.0.1.dist-info/WHEEL
uk_modulus_check-0.0.1.dist-info/top_level.txt
uk_modulus_check-0.0.1.dist-info/RECORD
